{
  "lookup.monster.name": "monster",
  "lookup.monster.description": "Looks up a monster.",
  "lookup.monster.name.name": "name",
  "lookup.monster.name.description": "What monster are you looking for?",

  "lookup.spell.name": "spell",
  "lookup.spell.description": "Looks up a spell.",
  "lookup.spell.name.name": "name",
  "lookup.spell.name.description": "What spell are you looking for?",

  "lookup.item.name": "item",
  "lookup.item.description": "Looks up an item.",
  "lookup.item.name.name": "name",
  "lookup.item.name.description": "What item are you looking for?",

  "lookup.feat.name": "feat",
  "lookup.feat.description": "Looks up a feat.",
  "lookup.feat.name.name": "name",
  "lookup.feat.name.description": "What feat are you looking for?",

  "lookup.deity.name": "deity",
  "lookup.deity.description": "Looks up a deity.",
  "lookup.deity.name.name": "name",
  "lookup.deity.name.description": "What deity are you looking for?",

  "lookup.object.name": "object",
  "lookup.object.description": "Looks up an object.",
  "lookup.object.name.name": "name",
  "lookup.object.name.description": "What object are you looking for?",

  "lookup.race.name": "race",
  "lookup.race.description": "Looks up a race.",
  "lookup.race.name.name": "name",
  "lookup.race.name.description": "What race are you looking for?",

  "lookup.condition.name": "condition",
  "lookup.condition.description": "Looks up a condition.",
  "lookup.condition.name.name": "name",
  "lookup.condition.name.description": "What condition are you looking for?",

  "lookup.magictable.name": "magictable",
  "lookup.magictable.description": "[Patron] Roll an item from the magic tables.",
  "lookup.magictable.table.name": "table",
  "lookup.magictable.table.description": "On which magic table do you want to roll?",

  "lookup.loot.name": "loot",
  "lookup.loot.description": "[Patron] Generate loot based on item rarity.",
  "lookup.loot.rarity.name": "name",
  "lookup.loot.rarity.description": "What item rarity do you want to roll?",

  "lookup.disease.name": "disease",
  "lookup.disease.description": "Looks up a disease.",
  "lookup.disease.name.name": "name",
  "lookup.disease.name.description": "What disease are you looking for?",

  "lookup.library.name": "library",
  "lookup.library.description": "Looks up books in the library.",
  "lookup.library.name.name": "name",
  "lookup.library.name.description": "What library do you want to see?",

  "lookup.rule.name": "rule",
  "lookup.rule.description": "Looks up a rule.",
  "lookup.rule.name.name": "name",
  "lookup.rule.name.description": "What rule are you looking for?",

  "lookup.racefeat.name": "racefeat",
  "lookup.racefeat.description": "Looks up a racial feature.",
  "lookup.racefeat.name.name": "name",
  "lookup.racefeat.name.description": "What racial feature are you looking for?",

  "lookup.classfeat.name": "classfeat",
  "lookup.classfeat.description": "Looks up a class feature.",
  "lookup.classfeat.name.name": "name",
  "lookup.classfeat.name.description": "What class feature are you looking for?",

  "lookup.skill.name": "skill",
  "lookup.skill.description": "Looks up a skill.",
  "lookup.skill.name.name": "name",
  "lookup.skill.name.description": "What skill are you looking for?",

  "lookup.class.name": "class",
  "lookup.class.description": "Looks up a class.",
  "lookup.class.name.name": "name",
  "lookup.class.name.description": "What class are you looking for?",

  "lookup.subclass.name": "subclass",
  "lookup.subclass.description": "Looks up a subclass.",
  "lookup.subclass.name.name": "name",
  "lookup.subclass.name.description": "What subclass are you looking for?",

  "lookup.background.name": "background",
  "lookup.background.description": "Looks up a background.",
  "lookup.background.name.name": "name",
  "lookup.background.name.description": "What background are you looking for?",

  "lookup.token.name": "token",
  "lookup.token.description": "Shows a token for a monster. May not support all monsters.",
  "lookup.token.name.name": "name",
  "lookup.token.name.description": "What token are you looking for?",

  "lookup.image.name": "image",
  "lookup.image.description": "Shows an image for a monster. May not support all monsters.",
  "lookup.image.name.name": "name",
  "lookup.image.name.description": "What image are you looking for?",

  "lookup.trap.name": "trap",
  "lookup.trap.description": "Looks up a trap.",
  "lookup.trap.name.name": "name",
  "lookup.trap.name.description": "What trap are you looking for?",

  "lookup.hazard.name": "hazard",
  "lookup.hazard.description": "Looks up a hazard.",
  "lookup.hazard.name.name": "name",
  "lookup.hazard.name.description": "What hazard are you looking for?",

  "lookup.cult.name": "cult",
  "lookup.cult.description": "Looks up a cult.",
  "lookup.cult.name.name": "name",
  "lookup.cult.name.description": "What cult are you looking for?",

  "lookup.boon.name": "boon",
  "lookup.boon.description": "Looks up a boon.",
  "lookup.boon.name.name": "name",
  "lookup.boon.name.description": "What boon are you looking for?",

  "lookup.reward.name": "reward",
  "lookup.reward.description": "Looks up a reward.",
  "lookup.reward.name.name": "name",
  "lookup.reward.name.description": "What reward are you looking for?"
}